yid_langchain_extensions/__init__.py
yid_langchain_extensions/utils.py
yid_langchain_extensions/llm/__init__.py
yid_langchain_extensions/llm/batches_openai_client.py
yid_langchain_extensions/llm/retrying_llm.py
yid_langchain_extensions/llm/tools_in_prompt_llm.py
yid_langchain_extensions/llm/tools_llm_with_thought.py
yid_langchain_extensions-0.7.5.dist-info/licenses/LICENSE
yid_langchain_extensions-0.7.5.dist-info/METADATA
yid_langchain_extensions-0.7.5.dist-info/WHEEL
yid_langchain_extensions-0.7.5.dist-info/top_level.txt
yid_langchain_extensions-0.7.5.dist-info/RECORD
